LICENSE
keras_flops/__init__.py
keras_flops/flops_calculation.py
keras_flops/flops_registory.py
keras_flops-0.1.2.dist-info/LICENSE
keras_flops-0.1.2.dist-info/WHEEL
keras_flops-0.1.2.dist-info/METADATA
keras_flops-0.1.2.dist-info/RECORD
