Metadata-Version: 2.1
Name: keras-flops
Version: 0.1.2
Summary: FLOPs calculator with tf.profiler for neural network architecture written in tensorflow 2.2+ (tf.keras)
Home-page: https://github.com/tokusumi/keras-flops
License: MIT
Keywords: tensorflow2,flops,profiler
Author: tokusumi
Author-email: tksmtoms@gmail.com
Requires-Python: >=3.6,<4.0
Classifier: License :: OSI Approved :: MIT License
Classifier: Operating System :: OS Independent
Classifier: Programming Language :: Python :: 3
Classifier: Programming Language :: Python :: 3 :: Only
Classifier: Programming Language :: Python :: 3.6
Classifier: Programming Language :: Python :: 3.7
Classifier: Programming Language :: Python :: 3.8
Classifier: Topic :: Scientific/Engineering :: Artificial Intelligence
Requires-Dist: tensorflow (>=2.2,<3.0)
Project-URL: Repository, https://github.com/tokusumi/keras-flops
